LICENSE.txt
MANIFEST.in
README.md
pyproject.toml
src/liwca/__init__.py
src/liwca/_remoteprocessors.py
src/liwca/io.py
src/liwca/liwc22.py
src/liwca.egg-info/PKG-INFO
src/liwca.egg-info/SOURCES.txt
src/liwca.egg-info/dependency_links.txt
src/liwca.egg-info/requires.txt
src/liwca.egg-info/top_level.txt
src/liwca/data/registry.txt