Metadata-Version: 2.1
Name: liwca
Version: 0.0.1a1
Summary: LIWC Assistant
Author-email: Remington Mallett <mallett.remy@gmail.com>
Maintainer-email: Remington Mallett <mallett.remy@gmail.com>
Project-URL: Homepage, https://github.com/remrama/liwca
Keywords: LIWC,text,language,datasets
Classifier: Development Status :: 1 - Planning
Classifier: License :: OSI Approved :: MIT License
Classifier: Operating System :: OS Independent
Classifier: Intended Audience :: Science/Research
Classifier: Topic :: Scientific/Engineering
Classifier: Programming Language :: Python
Classifier: Programming Language :: Python :: 3
Classifier: Programming Language :: Python :: 3.8
Classifier: Programming Language :: Python :: 3.9
Classifier: Programming Language :: Python :: 3.10
Classifier: Programming Language :: Python :: 3.11
Classifier: Programming Language :: Python :: 3.12
Classifier: Programming Language :: Python :: 3.13
Requires-Python: >=3.8
License-File: LICENSE.txt
Requires-Dist: pandas>=2.0
Requires-Dist: pandera>=0.20
Requires-Dist: pooch>=1.8
Requires-Dist: psutil>=6.0
Provides-Extra: dev
Requires-Dist: ruff; extra == "dev"
Requires-Dist: pydata-sphinx-theme; extra == "dev"
Requires-Dist: sphinx; extra == "dev"
Requires-Dist: sphinx_copybutton; extra == "dev"
Requires-Dist: sphinx-design; extra == "dev"
